fusesoc/plugin.py
pytest_cocotb_fusesoc-0.0.1.dist-info/METADATA
pytest_cocotb_fusesoc-0.0.1.dist-info/WHEEL
pytest_cocotb_fusesoc-0.0.1.dist-info/entry_points.txt
pytest_cocotb_fusesoc-0.0.1.dist-info/RECORD
